yaart/__init__.py
yaart/db.py
yaart/llm.py
yaart/models.py
yaart/optimizer.py
yaart/prompts.py
yaart/scraper.py
yaart-1.0.0.dist-info/LICENSE
yaart-1.0.0.dist-info/METADATA
yaart-1.0.0.dist-info/WHEEL
yaart-1.0.0.dist-info/RECORD
