Metadata-Version: 2.1
Name: yaart
Version: 1.0.0
Summary: Yet Another AI Resume Tool
Author: Justin Flick
Author-email: Justinjayflick@gmail.com
Requires-Python: >=3.9,<4.0
Classifier: Programming Language :: Python :: 3
Classifier: Programming Language :: Python :: 3.9
Classifier: Programming Language :: Python :: 3.10
Classifier: Programming Language :: Python :: 3.11
Requires-Dist: beautifulsoup4 (>=4.12.3,<5.0.0)
Requires-Dist: httpx (>=0.27.0,<0.28.0)
Requires-Dist: langchain (>=0.3.13,<0.4.0)
Requires-Dist: langchain-anthropic (>=0.3.1,<0.4.0)
Requires-Dist: langchain-community (>=0.3.13,<0.4.0)
Requires-Dist: langchain-core (>=0.3.28,<0.4.0)
Requires-Dist: langchain-openai (>=0.2.14,<0.3.0)
Requires-Dist: markdown (>=3.6,<4.0)
Requires-Dist: md2pdf (>=1.0.1,<2.0.0)
Requires-Dist: openai (>=1.35.10,<2.0.0)
Requires-Dist: rich (>=13.7.1,<14.0.0)
